{
    "$schema": "https://schema.management.azure.com/schemas/2019-04-01/deploymentTemplate.json#",
    "contentVersion": "1.0.0.0",
    "parameters": {
        "projectName": {
            "type": "string",
            "metadata": {
                "description": "The name of the project. This string will be used to name the virtual machine and associated resources."
            }
        },
        "environmentName": {
            "type": "string",
            "defaultValue": "dev",
            "allowedValues": [
                "sandbox",
                "dev",
                "staging",
                "prod",
                "SANDBOX",
                "DEV",
                "STAGING",
                "PROD"
            ],
            "metadata": {
                "description": "The environment of the whole solution."
            }
        },
        "vmComputerName": {
            "type": "string",
            "metadata": {
                "description": "The computer name of the virtual machine's OS. Windows computer name cannot be more than 15 characters long, be entirely numeric, or contain these characters: ` ~ ! @ # $ %25 ^ & * ( ) = + _ [ ] { } \\ | ; : . ' \" , < > / ?."
            }
        },
        "vmPurpose": {
            "type": "string",
            "metadata": {
                "description": "The purpose of the virtual machine. ex: App (application), Data (database)"
            }
        },
        "vmNumber": {
            "type": "string",

            "metadata": {
                "description": "The number of the virtual machine. This number will be used to name the virtual machine. (ex: 01)"
            }
        },
        "vmSize": {
            "type": "string",
            "defaultValue": "Standard_B2S",
            "metadata": {
                "description": "The size of the virtual machine. ex: Standard_B2s"
            }
        },
        "vmOSVersion": {
            "type": "string",
            "defaultValue": "2016-Datacenter",
            "metadata": {
                "description": "The OS version of the virtual machine. ex: 2016-Datacenter"
            }
        },
        "vmOSDiskType": {
            "type": "string",
            "defaultValue": "Premium_LRS",
            "allowedValues": [
                "Standard_LRS",
                "Premium_LRS",
                "StandardSSD_LRS"
            ],
            "metadata": {
                "description": "The disk type of the virtual machine's OS Disk."
            }
        },
        "vmDiskSize": {
            "type": "int",
            "defaultValue": 100,
            "metadata": {
                "description": "The size (GB) of the data disk of the virtual machine."
            }
        },
        "vmAutomaticUpdates": {
            "type": "bool",
            "defaultValue": true,
            "metadata": {
                "description": "Should automatic updates be enable on the virtual machine. true or false"
            }
        },
        "adminUsername": {
            "type": "string",
            "metadata": {
                "description": "The username of the default admin account."
            }
        },
        "adminPassword": {
            "type": "secureString",
            "metadata": {
                "description": "The password of the default admin account."
            }
        },
        "publicIpAddressType": {
            "type": "string",
            "defaultValue": "static",
            "allowedValues": [
                "static",
                "dynamic"
            ],
            "metadata": {
                "description": "The type of the public ip. ex: static or dynamic"
            }
        },
        "publicIpAddressSku": {
            "type": "string",
            "defaultValue": "basic",
            "allowedValues": [
                "basic",
                "standard"
            ],
            "metadata": {
                "description": "The SKU of the public ip. ex: basic or standard"
            }
        },
        "diagnosticsStorageAccountName": {
            "type": "string",
            "metadata": {
                "description": "The name of the diagnostic storage account to be created for your virtual machine.  Suggested format: [short project name][vmpurpose]diagsa"
            }
        },
        "vnetRG": {
            "type": "string",
            "metadata": {
                "description": "The name of the resource group containing the virtual network where the virtual machine will be created."
            }
        },
        "vnetName": {
            "type": "string",
            "metadata": {
                "description": "The name of the virtual network where the virtual machine will be created."
            }
        },
        "subnetName": {
            "type": "string",
            "metadata": {
                "description": "The name of the pre-created subnet. ex: example-SN"
            }
        }
    },
    "functions": [
        {
            "namespace": "env",
            "members": {
                "transform": {
                    "parameters": [
                        {
                            "name": "env",
                            "type": "string"
                        }
                    ],
                    "output": {
                        "type": "string",
                        "value": "[if(equals(toUpper(parameters('env')), 'PROD'), '', concat('-', toUpper(parameters('env'))))]"
                    }
                }
            }
        },
        {
            "namespace": "name",
            "members": {
                "clean": {
                    "parameters": [
                        {
                            "name": "name",
                            "type": "string"
                        }
                    ],
                    "output": {
                        "type": "string",
                        "value": "[replace(replace(replace(parameters('name'), '-', ''), '_', ''), ' ', '')]"
                    }
                }
            }
        }
    ],
    "variables": {
        "vm_name": "[concat(name.clean(parameters('projectName')), '-', parameters('vmPurpose'), parameters('vmNumber'), env.transform(parameters('environmentName')), '-VM')]",
        "vm_publicip_name": "[concat(name.clean(parameters('projectName')), parameters('vmPurpose'), parameters('vmNumber'),env.transform(parameters('environmentName')), '-PublicIP')]",
        "vm_nic_name": "[concat(name.clean(parameters('projectName')), parameters('vmPurpose'), parameters('vmNumber'),env.transform(parameters('environmentName')), '-NIC')]",
        "vm_os_disk_name": "[concat(name.clean(parameters('projectName')), parameters('vmPurpose'), parameters('vmNumber'),env.transform(parameters('environmentName')), '-OSDisk')]",
        "vm_data_disk_name": "[concat(name.clean(parameters('projectName')), parameters('vmPurpose'), parameters('vmNumber'),env.transform(parameters('environmentName')), '-DataDisk')]"
    },
    "resources": [
        {
            "type": "Microsoft.Network/networkInterfaces",
            "name": "[variables('vm_nic_name')]",
            "apiVersion": "2019-07-01",
            "location": "canada central",
            "dependsOn": [
                "[resourceId('Microsoft.Network/publicIpAddresses',variables('vm_publicip_name'))]"
            ],
            "properties": {
                "ipConfigurations": [
                    {
                        "name": "ipconfig",
                        "properties": {
                            "subnet": {
                                "id": "[resourceId(parameters('vnetRG'),'Microsoft.Network/virtualNetworks/subnets', parameters('vnetName'), parameters('subnetName'))]"
                            },
                            "privateIPAllocationMethod": "Dynamic",
                            "publicIpAddress": {
                                "id": "[resourceId(resourceGroup().name, 'Microsoft.Network/publicIpAddresses', variables('vm_publicip_name'))]"
                            }
                        }
                    }
                ]
            }
        },
        {
            "type": "Microsoft.Network/publicIpAddresses",
            "name": "[variables('vm_publicip_name')]",
            "apiVersion": "2019-02-01",
            "location": "canada central",
            "properties": {
                "publicIpAllocationMethod": "[parameters('publicIpAddressType')]"
            },
            "sku": {
                "name": "[parameters('publicIpAddressSku')]"
            }
        },
        {
            "type": "Microsoft.Storage/storageAccounts",
            "apiVersion": "2019-06-01",
            "name": "[parameters('diagnosticsStorageAccountName')]",
            "location": "Canada Central",
            "sku": {
                "name": "Standard_LRS"
            },
            "kind": "Storage",
            "properties": {}
        },
        {
            "type": "Microsoft.Compute/virtualMachines",
            "name": "[variables('vm_name')]",
            "apiVersion": "2019-07-01",
            "location": "canada central",
            "tags": {},
            "dependsOn": [
                "[resourceId('Microsoft.Network/networkInterfaces/', variables('vm_nic_name'))]",
                "[resourceId('Microsoft.Storage/storageAccounts',parameters('diagnosticsStorageAccountName'))]"
            ],
            "properties": {
                "hardwareProfile": {
                    "vmSize": "[parameters('vmSize')]"
                },
                "storageProfile": {
                    "osDisk": {
                        "osType":"Windows",
                        "name": "[variables('vm_os_disk_name')]",
                        "createOption": "fromImage",
                        "managedDisk": {
                            "storageAccountType": "[parameters('vmOSDiskType')]"
                        }
                    },
                    "imageReference": {
                        "publisher": "MicrosoftWindowsServer",
                        "offer": "WindowsServer",
                        "sku": "[parameters('vmOSVersion')]",
                        "version": "latest"
                    },
                    "dataDisks": [{
                        "name": "[variables('vm_data_disk_name')]",
                        "diskSizeGB": "[parameters('vmDiskSize')]",
                        "lun": 0,
                        "createOption": "Empty"
                    }]
                },
                "networkProfile": {
                    "networkInterfaces": [
                        {
                            "id": "[resourceId('Microsoft.Network/networkInterfaces', variables('vm_nic_name'))]"
                        }
                    ]
                },
                "osProfile": {
                    "computerName": "[parameters('vmComputerName')]",
                    "adminUsername": "[parameters('adminUsername')]",
                    "adminPassword": "[parameters('adminPassword')]",
                    "windowsConfiguration": {
                        "enableAutomaticUpdates": "[parameters('vmAutomaticUpdates')]",
                        "timeZone":"Eastern Standard Time"
                    }
                },
                "diagnosticsProfile": {
                    "bootDiagnostics": {
                        "enabled": true,
                        "storageUri": "[concat('https://', parameters('diagnosticsStorageAccountName'), '.blob.core.windows.net/')]"
                    }
                }
            }
        }
    ],
    "outputs": {
        "vmName": {
            "type": "string",
            "value": "[variables('vm_name')]"
        },
        "vmID": {
            "type": "string",
            "value": "[resourceId('Microsoft.Compute/virtualMachines',variables('vm_name'))]"
        },
        "nicName": {
            "type": "string",
            "value": "[variables('vm_nic_name')]"
        },
        "nicID": {
            "type": "string",
            "value": "[resourceId('Microsoft.Network/networkInterfaces',variables('vm_nic_name'))]"
        },
        "publicipName": {
            "type": "string",
            "value": "[variables('vm_publicip_name')]"
        },
        "publicipID": {
            "type": "string",
            "value": "[resourceId('Microsoft.Network/publicIpAddresses',variables('vm_publicip_name'))]"
        },
        "diagstorageaccountName": {
            "type": "string",
            "value": "[parameters('diagnosticsStorageAccountName')]"
        },
        "diagstorageaccountID": {
            "type": "string",
            "value": "[resourceId('Microsoft.Storage/storageAccounts',parameters('diagnosticsStorageAccountName'))]"
        }
    }
}